{
	"id": 368,
	"name": "store-models",
	"variant": "project",
	"kind": 1,
	"flags": {},
	"comment": {
		"summary": [
			{
				"text": "## Relations Overview\n\n",
				"kind": "text"
			},
			{
				"text": "```mermaid\nerDiagram\n\tStore ||--|| StoreCurrency : supported_currencies\n\tStore ||--|| StoreLocale : supported_locales\n\n```",
				"kind": "code"
			}
		]
	},
	"children": [
		{
			"id": 401,
			"name": "StoreCurrency",
			"variant": "declaration",
			"kind": 32,
			"flags": {
				"isConst": true
			},
			"sources": [
				{
					"fileName": "currency.ts",
					"line": 4,
					"character": 6,
					"url": "https://github.com/medusajs/medusa/blob/8bd1d22765edef3b3d2ff31c8f8935049d8b280a/packages/modules/store/src/models/currency.ts#L4"
				}
			],
			"type": {
				"type": "reference",
				"target": {
					"sourceFileName": "../../../../packages/core/utils/src/dml/entity.ts",
					"qualifiedName": "DmlEntity"
				},
				"typeArguments": [
					{
						"type": "reference",
						"target": {
							"sourceFileName": "../../../../packages/core/utils/src/dml/entity.ts",
							"qualifiedName": "DMLEntitySchemaBuilder"
						},
						"typeArguments": [
							{
								"type": "reflection",
								"declaration": {
									"id": 402,
									"name": "__type",
									"variant": "declaration",
									"kind": 65536,
									"flags": {},
									"children": [
										{
											"id": 403,
											"name": "id",
											"variant": "declaration",
											"kind": 1024,
											"flags": {},
											"comment": {
												"summary": [
													{
														"kind": "text",
														"text": "The ID of the currency."
													}
												]
											},
											"sources": [
												{
													"fileName": "currency.ts",
													"line": 5,
													"character": 2,
													"url": "https://github.com/medusajs/medusa/blob/8bd1d22765edef3b3d2ff31c8f8935049d8b280a/packages/modules/store/src/models/currency.ts#L5"
												}
											],
											"type": {
												"type": "reference",
												"target": {
													"sourceFileName": "../../../../packages/core/utils/src/dml/properties/primary-key.ts",
													"qualifiedName": "PrimaryKeyModifier"
												},
												"typeArguments": [
													{
														"type": "reference",
														"target": {
															"sourceFileName": "../../../../packages/core/utils/src/dml/properties/id.ts",
															"qualifiedName": "IdProperty"
														},
														"name": "IdProperty",
														"package": "@medusajs/utils"
													}
												],
												"name": "PrimaryKeyModifier",
												"package": "@medusajs/utils"
											},
											"defaultValue": "..."
										},
										{
											"id": 404,
											"name": "currency_code",
											"variant": "declaration",
											"kind": 1024,
											"flags": {},
											"comment": {
												"summary": [
													{
														"kind": "text",
														"text": "The ISO 3 currency code. For example, `usd`."
													}
												]
											},
											"sources": [
												{
													"fileName": "currency.ts",
													"line": 6,
													"character": 2,
													"url": "https://github.com/medusajs/medusa/blob/8bd1d22765edef3b3d2ff31c8f8935049d8b280a/packages/modules/store/src/models/currency.ts#L6"
												}
											],
											"type": {
												"type": "reference",
												"target": {
													"sourceFileName": "../../../../packages/core/utils/src/dml/properties/text.ts",
													"qualifiedName": "TextProperty"
												},
												"name": "TextProperty",
												"package": "@medusajs/utils"
											},
											"defaultValue": "..."
										},
										{
											"id": 405,
											"name": "is_default",
											"variant": "declaration",
											"kind": 1024,
											"flags": {},
											"comment": {
												"summary": [
													{
														"kind": "text",
														"text": "Whether the currency is the default in the store."
													}
												]
											},
											"sources": [
												{
													"fileName": "currency.ts",
													"line": 7,
													"character": 2,
													"url": "https://github.com/medusajs/medusa/blob/8bd1d22765edef3b3d2ff31c8f8935049d8b280a/packages/modules/store/src/models/currency.ts#L7"
												}
											],
											"type": {
												"type": "reference",
												"target": {
													"sourceFileName": "../../../../packages/core/utils/src/dml/properties/boolean.ts",
													"qualifiedName": "BooleanProperty"
												},
												"name": "BooleanProperty",
												"package": "@medusajs/utils"
											},
											"defaultValue": "..."
										},
										{
											"id": 406,
											"name": "store",
											"variant": "declaration",
											"kind": 1024,
											"flags": {
												"isOptional": true
											},
											"comment": {
												"summary": [
													{
														"kind": "text",
														"text": "The store this currency belongs to."
													}
												]
											},
											"sources": [
												{
													"fileName": "currency.ts",
													"line": 8,
													"character": 2,
													"url": "https://github.com/medusajs/medusa/blob/8bd1d22765edef3b3d2ff31c8f8935049d8b280a/packages/modules/store/src/models/currency.ts#L8"
												}
											],
											"type": {
												"type": "reference",
												"target": {
													"sourceFileName": "../../../../packages/core/utils/src/dml/relations/belongs-to.ts",
													"qualifiedName": "BelongsTo"
												},
												"typeArguments": [
													{
														"type": "reference",
														"target": 369,
														"name": "Store"
													}
												],
												"name": "BelongsTo",
												"package": "@medusajs/utils"
											},
											"defaultValue": "..."
										}
									],
									"groups": [
										{
											"title": "Properties",
											"children": [
												403,
												404,
												405,
												406
											]
										}
									],
									"sources": [
										{
											"fileName": "currency.ts",
											"line": 4,
											"character": 52,
											"url": "https://github.com/medusajs/medusa/blob/8bd1d22765edef3b3d2ff31c8f8935049d8b280a/packages/modules/store/src/models/currency.ts#L4"
										}
									]
								}
							}
						],
						"name": "DMLEntitySchemaBuilder",
						"package": "@medusajs/utils"
					},
					{
						"type": "literal",
						"value": "StoreCurrency"
					}
				],
				"name": "DmlEntity",
				"package": "@medusajs/utils"
			},
			"defaultValue": "..."
		},
		{
			"id": 437,
			"name": "StoreLocale",
			"variant": "declaration",
			"kind": 32,
			"flags": {
				"isConst": true
			},
			"sources": [
				{
					"fileName": "locale.ts",
					"line": 4,
					"character": 6,
					"url": "https://github.com/medusajs/medusa/blob/8bd1d22765edef3b3d2ff31c8f8935049d8b280a/packages/modules/store/src/models/locale.ts#L4"
				}
			],
			"type": {
				"type": "reference",
				"target": {
					"sourceFileName": "../../../../packages/core/utils/src/dml/entity.ts",
					"qualifiedName": "DmlEntity"
				},
				"typeArguments": [
					{
						"type": "reference",
						"target": {
							"sourceFileName": "../../../../packages/core/utils/src/dml/entity.ts",
							"qualifiedName": "DMLEntitySchemaBuilder"
						},
						"typeArguments": [
							{
								"type": "reflection",
								"declaration": {
									"id": 438,
									"name": "__type",
									"variant": "declaration",
									"kind": 65536,
									"flags": {},
									"children": [
										{
											"id": 439,
											"name": "id",
											"variant": "declaration",
											"kind": 1024,
											"flags": {},
											"sources": [
												{
													"fileName": "locale.ts",
													"line": 5,
													"character": 2,
													"url": "https://github.com/medusajs/medusa/blob/8bd1d22765edef3b3d2ff31c8f8935049d8b280a/packages/modules/store/src/models/locale.ts#L5"
												}
											],
											"type": {
												"type": "reference",
												"target": {
													"sourceFileName": "../../../../packages/core/utils/src/dml/properties/primary-key.ts",
													"qualifiedName": "PrimaryKeyModifier"
												},
												"typeArguments": [
													{
														"type": "reference",
														"target": {
															"sourceFileName": "../../../../packages/core/utils/src/dml/properties/id.ts",
															"qualifiedName": "IdProperty"
														},
														"name": "IdProperty",
														"package": "@medusajs/utils"
													}
												],
												"name": "PrimaryKeyModifier",
												"package": "@medusajs/utils"
											},
											"defaultValue": "..."
										},
										{
											"id": 440,
											"name": "locale_code",
											"variant": "declaration",
											"kind": 1024,
											"flags": {},
											"sources": [
												{
													"fileName": "locale.ts",
													"line": 6,
													"character": 2,
													"url": "https://github.com/medusajs/medusa/blob/8bd1d22765edef3b3d2ff31c8f8935049d8b280a/packages/modules/store/src/models/locale.ts#L6"
												}
											],
											"type": {
												"type": "reference",
												"target": {
													"sourceFileName": "../../../../packages/core/utils/src/dml/properties/text.ts",
													"qualifiedName": "TextProperty"
												},
												"name": "TextProperty",
												"package": "@medusajs/utils"
											},
											"defaultValue": "..."
										},
										{
											"id": 441,
											"name": "is_default",
											"variant": "declaration",
											"kind": 1024,
											"flags": {},
											"sources": [
												{
													"fileName": "locale.ts",
													"line": 7,
													"character": 2,
													"url": "https://github.com/medusajs/medusa/blob/8bd1d22765edef3b3d2ff31c8f8935049d8b280a/packages/modules/store/src/models/locale.ts#L7"
												}
											],
											"type": {
												"type": "reference",
												"target": {
													"sourceFileName": "../../../../packages/core/utils/src/dml/properties/boolean.ts",
													"qualifiedName": "BooleanProperty"
												},
												"name": "BooleanProperty",
												"package": "@medusajs/utils"
											},
											"defaultValue": "..."
										},
										{
											"id": 442,
											"name": "store",
											"variant": "declaration",
											"kind": 1024,
											"flags": {
												"isOptional": true
											},
											"sources": [
												{
													"fileName": "locale.ts",
													"line": 8,
													"character": 2,
													"url": "https://github.com/medusajs/medusa/blob/8bd1d22765edef3b3d2ff31c8f8935049d8b280a/packages/modules/store/src/models/locale.ts#L8"
												}
											],
											"type": {
												"type": "reference",
												"target": {
													"sourceFileName": "../../../../packages/core/utils/src/dml/relations/belongs-to.ts",
													"qualifiedName": "BelongsTo"
												},
												"typeArguments": [
													{
														"type": "reference",
														"target": 369,
														"name": "Store"
													}
												],
												"name": "BelongsTo",
												"package": "@medusajs/utils"
											},
											"defaultValue": "..."
										}
									],
									"groups": [
										{
											"title": "Properties",
											"children": [
												439,
												440,
												441,
												442
											]
										}
									],
									"sources": [
										{
											"fileName": "locale.ts",
											"line": 4,
											"character": 48,
											"url": "https://github.com/medusajs/medusa/blob/8bd1d22765edef3b3d2ff31c8f8935049d8b280a/packages/modules/store/src/models/locale.ts#L4"
										}
									]
								}
							}
						],
						"name": "DMLEntitySchemaBuilder",
						"package": "@medusajs/utils"
					},
					{
						"type": "literal",
						"value": "StoreLocale"
					}
				],
				"name": "DmlEntity",
				"package": "@medusajs/utils"
			},
			"defaultValue": "..."
		},
		{
			"id": 369,
			"name": "Store",
			"variant": "declaration",
			"kind": 32,
			"flags": {
				"isConst": true
			},
			"sources": [
				{
					"fileName": "store.ts",
					"line": 5,
					"character": 6,
					"url": "https://github.com/medusajs/medusa/blob/8bd1d22765edef3b3d2ff31c8f8935049d8b280a/packages/modules/store/src/models/store.ts#L5"
				}
			],
			"type": {
				"type": "reference",
				"target": {
					"sourceFileName": "../../../../packages/core/utils/src/dml/entity.ts",
					"qualifiedName": "DmlEntity"
				},
				"typeArguments": [
					{
						"type": "reference",
						"target": {
							"sourceFileName": "../../../../packages/core/utils/src/dml/entity.ts",
							"qualifiedName": "DMLEntitySchemaBuilder"
						},
						"typeArguments": [
							{
								"type": "reflection",
								"declaration": {
									"id": 370,
									"name": "__type",
									"variant": "declaration",
									"kind": 65536,
									"flags": {},
									"children": [
										{
											"id": 371,
											"name": "id",
											"variant": "declaration",
											"kind": 1024,
											"flags": {},
											"comment": {
												"summary": [
													{
														"kind": "text",
														"text": "The ID of the store."
													}
												]
											},
											"sources": [
												{
													"fileName": "store.ts",
													"line": 7,
													"character": 4,
													"url": "https://github.com/medusajs/medusa/blob/8bd1d22765edef3b3d2ff31c8f8935049d8b280a/packages/modules/store/src/models/store.ts#L7"
												}
											],
											"type": {
												"type": "reference",
												"target": {
													"sourceFileName": "../../../../packages/core/utils/src/dml/properties/primary-key.ts",
													"qualifiedName": "PrimaryKeyModifier"
												},
												"typeArguments": [
													{
														"type": "reference",
														"target": {
															"sourceFileName": "../../../../packages/core/utils/src/dml/properties/id.ts",
															"qualifiedName": "IdProperty"
														},
														"name": "IdProperty",
														"package": "@medusajs/utils"
													}
												],
												"name": "PrimaryKeyModifier",
												"package": "@medusajs/utils"
											},
											"defaultValue": "..."
										},
										{
											"id": 372,
											"name": "name",
											"variant": "declaration",
											"kind": 1024,
											"flags": {},
											"comment": {
												"summary": [
													{
														"kind": "text",
														"text": "The name of the store"
													}
												]
											},
											"sources": [
												{
													"fileName": "store.ts",
													"line": 8,
													"character": 4,
													"url": "https://github.com/medusajs/medusa/blob/8bd1d22765edef3b3d2ff31c8f8935049d8b280a/packages/modules/store/src/models/store.ts#L8"
												}
											],
											"type": {
												"type": "reference",
												"target": {
													"sourceFileName": "../../../../packages/core/utils/src/dml/properties/text.ts",
													"qualifiedName": "TextProperty"
												},
												"name": "TextProperty",
												"package": "@medusajs/utils"
											},
											"defaultValue": "..."
										},
										{
											"id": 373,
											"name": "default_sales_channel_id",
											"variant": "declaration",
											"kind": 1024,
											"flags": {
												"isOptional": true
											},
											"comment": {
												"summary": [
													{
														"kind": "text",
														"text": "The ID of the store's default sales channel."
													}
												]
											},
											"sources": [
												{
													"fileName": "store.ts",
													"line": 9,
													"character": 4,
													"url": "https://github.com/medusajs/medusa/blob/8bd1d22765edef3b3d2ff31c8f8935049d8b280a/packages/modules/store/src/models/store.ts#L9"
												}
											],
											"type": {
												"type": "reference",
												"target": {
													"sourceFileName": "../../../../packages/core/utils/src/dml/properties/text.ts",
													"qualifiedName": "TextProperty"
												},
												"name": "TextProperty",
												"package": "@medusajs/utils"
											},
											"defaultValue": "..."
										},
										{
											"id": 374,
											"name": "default_region_id",
											"variant": "declaration",
											"kind": 1024,
											"flags": {
												"isOptional": true
											},
											"comment": {
												"summary": [
													{
														"kind": "text",
														"text": "The ID of the store's default region."
													}
												]
											},
											"sources": [
												{
													"fileName": "store.ts",
													"line": 10,
													"character": 4,
													"url": "https://github.com/medusajs/medusa/blob/8bd1d22765edef3b3d2ff31c8f8935049d8b280a/packages/modules/store/src/models/store.ts#L10"
												}
											],
											"type": {
												"type": "reference",
												"target": {
													"sourceFileName": "../../../../packages/core/utils/src/dml/properties/text.ts",
													"qualifiedName": "TextProperty"
												},
												"name": "TextProperty",
												"package": "@medusajs/utils"
											},
											"defaultValue": "..."
										},
										{
											"id": 375,
											"name": "default_location_id",
											"variant": "declaration",
											"kind": 1024,
											"flags": {
												"isOptional": true
											},
											"comment": {
												"summary": [
													{
														"kind": "text",
														"text": "The ID of the store's default stock location."
													}
												]
											},
											"sources": [
												{
													"fileName": "store.ts",
													"line": 11,
													"character": 4,
													"url": "https://github.com/medusajs/medusa/blob/8bd1d22765edef3b3d2ff31c8f8935049d8b280a/packages/modules/store/src/models/store.ts#L11"
												}
											],
											"type": {
												"type": "reference",
												"target": {
													"sourceFileName": "../../../../packages/core/utils/src/dml/properties/text.ts",
													"qualifiedName": "TextProperty"
												},
												"name": "TextProperty",
												"package": "@medusajs/utils"
											},
											"defaultValue": "..."
										},
										{
											"id": 376,
											"name": "metadata",
											"variant": "declaration",
											"kind": 1024,
											"flags": {
												"isOptional": true
											},
											"comment": {
												"summary": [
													{
														"kind": "text",
														"text": "Holds custom data in key-value pairs."
													}
												]
											},
											"sources": [
												{
													"fileName": "store.ts",
													"line": 12,
													"character": 4,
													"url": "https://github.com/medusajs/medusa/blob/8bd1d22765edef3b3d2ff31c8f8935049d8b280a/packages/modules/store/src/models/store.ts#L12"
												}
											],
											"type": {
												"type": "reference",
												"target": {
													"sourceFileName": "../../../../packages/core/utils/src/dml/properties/json.ts",
													"qualifiedName": "JSONProperty"
												},
												"name": "JSONProperty",
												"package": "@medusajs/utils"
											},
											"defaultValue": "..."
										},
										{
											"id": 377,
											"name": "supported_currencies",
											"variant": "declaration",
											"kind": 1024,
											"flags": {},
											"comment": {
												"summary": [
													{
														"kind": "text",
														"text": "The associated supported_currencies."
													}
												],
												"modifierTags": [
													"@expandable"
												]
											},
											"sources": [
												{
													"fileName": "store.ts",
													"line": 13,
													"character": 4,
													"url": "https://github.com/medusajs/medusa/blob/8bd1d22765edef3b3d2ff31c8f8935049d8b280a/packages/modules/store/src/models/store.ts#L13"
												}
											],
											"type": {
												"type": "reference",
												"target": {
													"sourceFileName": "../../../../packages/core/utils/src/dml/relations/has-many.ts",
													"qualifiedName": "HasMany"
												},
												"typeArguments": [
													{
														"type": "reference",
														"target": 401,
														"name": "StoreCurrency"
													}
												],
												"name": "HasMany",
												"package": "@medusajs/utils"
											},
											"defaultValue": "..."
										},
										{
											"id": 389,
											"name": "supported_locales",
											"variant": "declaration",
											"kind": 1024,
											"flags": {},
											"sources": [
												{
													"fileName": "store.ts",
													"line": 16,
													"character": 4,
													"url": "https://github.com/medusajs/medusa/blob/8bd1d22765edef3b3d2ff31c8f8935049d8b280a/packages/modules/store/src/models/store.ts#L16"
												}
											],
											"type": {
												"type": "reference",
												"target": {
													"sourceFileName": "../../../../packages/core/utils/src/dml/relations/has-many.ts",
													"qualifiedName": "HasMany"
												},
												"typeArguments": [
													{
														"type": "reference",
														"target": 437,
														"name": "StoreLocale"
													}
												],
												"name": "HasMany",
												"package": "@medusajs/utils"
											},
											"defaultValue": "..."
										}
									],
									"groups": [
										{
											"title": "Properties",
											"children": [
												371,
												372,
												373,
												374,
												375,
												376,
												377,
												389
											]
										}
									],
									"sources": [
										{
											"fileName": "store.ts",
											"line": 6,
											"character": 19,
											"url": "https://github.com/medusajs/medusa/blob/8bd1d22765edef3b3d2ff31c8f8935049d8b280a/packages/modules/store/src/models/store.ts#L6"
										}
									]
								}
							}
						],
						"name": "DMLEntitySchemaBuilder",
						"package": "@medusajs/utils"
					},
					{
						"type": "literal",
						"value": "Store"
					}
				],
				"name": "DmlEntity",
				"package": "@medusajs/utils"
			},
			"defaultValue": "..."
		}
	],
	"groups": [
		{
			"title": "Variables",
			"children": [
				401,
				437,
				369
			]
		}
	],
	"packageName": "@medusajs/store",
	"symbolIdMap": {
		"368": {
			"sourceFileName": "../../../../packages/modules/store/src/models/index.ts",
			"qualifiedName": ""
		},
		"369": {
			"sourceFileName": "../../../../packages/modules/store/src/models/store.ts",
			"qualifiedName": "Store"
		},
		"370": {
			"sourceFileName": "../../../../packages/modules/store/src/models/store.ts",
			"qualifiedName": "__object"
		},
		"371": {
			"sourceFileName": "../../../../packages/modules/store/src/models/store.ts",
			"qualifiedName": "__object.id"
		},
		"372": {
			"sourceFileName": "../../../../packages/modules/store/src/models/store.ts",
			"qualifiedName": "__object.name"
		},
		"373": {
			"sourceFileName": "../../../../packages/modules/store/src/models/store.ts",
			"qualifiedName": "__object.default_sales_channel_id"
		},
		"374": {
			"sourceFileName": "../../../../packages/modules/store/src/models/store.ts",
			"qualifiedName": "__object.default_region_id"
		},
		"375": {
			"sourceFileName": "../../../../packages/modules/store/src/models/store.ts",
			"qualifiedName": "__object.default_location_id"
		},
		"376": {
			"sourceFileName": "../../../../packages/modules/store/src/models/store.ts",
			"qualifiedName": "__object.metadata"
		},
		"377": {
			"sourceFileName": "../../../../packages/modules/store/src/models/store.ts",
			"qualifiedName": "__object.supported_currencies"
		},
		"378": {
			"sourceFileName": "../../../../packages/modules/store/src/models/store.ts",
			"qualifiedName": "__function"
		},
		"379": {
			"sourceFileName": "../../../../packages/modules/store/src/models/store.ts",
			"qualifiedName": "__function"
		},
		"380": {
			"sourceFileName": "../../../../packages/modules/store/src/models/currency.ts",
			"qualifiedName": "__object"
		},
		"381": {
			"sourceFileName": "../../../../packages/modules/store/src/models/currency.ts",
			"qualifiedName": "__object.id"
		},
		"382": {
			"sourceFileName": "../../../../packages/modules/store/src/models/currency.ts",
			"qualifiedName": "__object.currency_code"
		},
		"383": {
			"sourceFileName": "../../../../packages/modules/store/src/models/currency.ts",
			"qualifiedName": "__object.is_default"
		},
		"384": {
			"sourceFileName": "../../../../packages/modules/store/src/models/currency.ts",
			"qualifiedName": "__object.store"
		},
		"385": {
			"sourceFileName": "../../../../packages/modules/store/src/models/currency.ts",
			"qualifiedName": "__function"
		},
		"386": {
			"sourceFileName": "../../../../packages/modules/store/src/models/currency.ts",
			"qualifiedName": "__function"
		},
		"387": {
			"sourceFileName": "../../../../packages/modules/store/src/models/currency.ts",
			"qualifiedName": "__function"
		},
		"388": {
			"sourceFileName": "../../../../packages/modules/store/src/models/currency.ts",
			"qualifiedName": "__function"
		},
		"389": {
			"sourceFileName": "../../../../packages/modules/store/src/models/store.ts",
			"qualifiedName": "__object.supported_locales"
		},
		"390": {
			"sourceFileName": "../../../../packages/modules/store/src/models/store.ts",
			"qualifiedName": "__function"
		},
		"391": {
			"sourceFileName": "../../../../packages/modules/store/src/models/store.ts",
			"qualifiedName": "__function"
		},
		"392": {
			"sourceFileName": "../../../../packages/modules/store/src/models/locale.ts",
			"qualifiedName": "__object"
		},
		"393": {
			"sourceFileName": "../../../../packages/modules/store/src/models/locale.ts",
			"qualifiedName": "__object.id"
		},
		"394": {
			"sourceFileName": "../../../../packages/modules/store/src/models/locale.ts",
			"qualifiedName": "__object.locale_code"
		},
		"395": {
			"sourceFileName": "../../../../packages/modules/store/src/models/locale.ts",
			"qualifiedName": "__object.is_default"
		},
		"396": {
			"sourceFileName": "../../../../packages/modules/store/src/models/locale.ts",
			"qualifiedName": "__object.store"
		},
		"397": {
			"sourceFileName": "../../../../packages/modules/store/src/models/locale.ts",
			"qualifiedName": "__function"
		},
		"398": {
			"sourceFileName": "../../../../packages/modules/store/src/models/locale.ts",
			"qualifiedName": "__function"
		},
		"399": {
			"sourceFileName": "../../../../packages/modules/store/src/models/locale.ts",
			"qualifiedName": "__function"
		},
		"400": {
			"sourceFileName": "../../../../packages/modules/store/src/models/locale.ts",
			"qualifiedName": "__function"
		},
		"401": {
			"sourceFileName": "../../../../packages/modules/store/src/models/currency.ts",
			"qualifiedName": "StoreCurrency"
		},
		"402": {
			"sourceFileName": "../../../../packages/modules/store/src/models/currency.ts",
			"qualifiedName": "__object"
		},
		"403": {
			"sourceFileName": "../../../../packages/modules/store/src/models/currency.ts",
			"qualifiedName": "__object.id"
		},
		"404": {
			"sourceFileName": "../../../../packages/modules/store/src/models/currency.ts",
			"qualifiedName": "__object.currency_code"
		},
		"405": {
			"sourceFileName": "../../../../packages/modules/store/src/models/currency.ts",
			"qualifiedName": "__object.is_default"
		},
		"406": {
			"sourceFileName": "../../../../packages/modules/store/src/models/currency.ts",
			"qualifiedName": "__object.store"
		},
		"407": {
			"sourceFileName": "../../../../packages/modules/store/src/models/currency.ts",
			"qualifiedName": "__function"
		},
		"408": {
			"sourceFileName": "../../../../packages/modules/store/src/models/currency.ts",
			"qualifiedName": "__function"
		},
		"409": {
			"sourceFileName": "../../../../packages/modules/store/src/models/store.ts",
			"qualifiedName": "__object"
		},
		"410": {
			"sourceFileName": "../../../../packages/modules/store/src/models/store.ts",
			"qualifiedName": "__object.id"
		},
		"411": {
			"sourceFileName": "../../../../packages/modules/store/src/models/store.ts",
			"qualifiedName": "__object.name"
		},
		"412": {
			"sourceFileName": "../../../../packages/modules/store/src/models/store.ts",
			"qualifiedName": "__object.default_sales_channel_id"
		},
		"413": {
			"sourceFileName": "../../../../packages/modules/store/src/models/store.ts",
			"qualifiedName": "__object.default_region_id"
		},
		"414": {
			"sourceFileName": "../../../../packages/modules/store/src/models/store.ts",
			"qualifiedName": "__object.default_location_id"
		},
		"415": {
			"sourceFileName": "../../../../packages/modules/store/src/models/store.ts",
			"qualifiedName": "__object.metadata"
		},
		"416": {
			"sourceFileName": "../../../../packages/modules/store/src/models/store.ts",
			"qualifiedName": "__object.supported_currencies"
		},
		"417": {
			"sourceFileName": "../../../../packages/modules/store/src/models/store.ts",
			"qualifiedName": "__function"
		},
		"418": {
			"sourceFileName": "../../../../packages/modules/store/src/models/store.ts",
			"qualifiedName": "__function"
		},
		"419": {
			"sourceFileName": "../../../../packages/modules/store/src/models/store.ts",
			"qualifiedName": "__object.supported_locales"
		},
		"420": {
			"sourceFileName": "../../../../packages/modules/store/src/models/store.ts",
			"qualifiedName": "__function"
		},
		"421": {
			"sourceFileName": "../../../../packages/modules/store/src/models/store.ts",
			"qualifiedName": "__function"
		},
		"422": {
			"sourceFileName": "../../../../packages/modules/store/src/models/currency.ts",
			"qualifiedName": "__function"
		},
		"423": {
			"sourceFileName": "../../../../packages/modules/store/src/models/currency.ts",
			"qualifiedName": "__function"
		},
		"424": {
			"sourceFileName": "../../../../packages/modules/store/src/models/store.ts",
			"qualifiedName": "__object"
		},
		"425": {
			"sourceFileName": "../../../../packages/modules/store/src/models/store.ts",
			"qualifiedName": "__object.id"
		},
		"426": {
			"sourceFileName": "../../../../packages/modules/store/src/models/store.ts",
			"qualifiedName": "__object.name"
		},
		"427": {
			"sourceFileName": "../../../../packages/modules/store/src/models/store.ts",
			"qualifiedName": "__object.default_sales_channel_id"
		},
		"428": {
			"sourceFileName": "../../../../packages/modules/store/src/models/store.ts",
			"qualifiedName": "__object.default_region_id"
		},
		"429": {
			"sourceFileName": "../../../../packages/modules/store/src/models/store.ts",
			"qualifiedName": "__object.default_location_id"
		},
		"430": {
			"sourceFileName": "../../../../packages/modules/store/src/models/store.ts",
			"qualifiedName": "__object.metadata"
		},
		"431": {
			"sourceFileName": "../../../../packages/modules/store/src/models/store.ts",
			"qualifiedName": "__object.supported_currencies"
		},
		"432": {
			"sourceFileName": "../../../../packages/modules/store/src/models/store.ts",
			"qualifiedName": "__function"
		},
		"433": {
			"sourceFileName": "../../../../packages/modules/store/src/models/store.ts",
			"qualifiedName": "__function"
		},
		"434": {
			"sourceFileName": "../../../../packages/modules/store/src/models/store.ts",
			"qualifiedName": "__object.supported_locales"
		},
		"435": {
			"sourceFileName": "../../../../packages/modules/store/src/models/store.ts",
			"qualifiedName": "__function"
		},
		"436": {
			"sourceFileName": "../../../../packages/modules/store/src/models/store.ts",
			"qualifiedName": "__function"
		},
		"437": {
			"sourceFileName": "../../../../packages/modules/store/src/models/locale.ts",
			"qualifiedName": "StoreLocale"
		},
		"438": {
			"sourceFileName": "../../../../packages/modules/store/src/models/locale.ts",
			"qualifiedName": "__object"
		},
		"439": {
			"sourceFileName": "../../../../packages/modules/store/src/models/locale.ts",
			"qualifiedName": "__object.id"
		},
		"440": {
			"sourceFileName": "../../../../packages/modules/store/src/models/locale.ts",
			"qualifiedName": "__object.locale_code"
		},
		"441": {
			"sourceFileName": "../../../../packages/modules/store/src/models/locale.ts",
			"qualifiedName": "__object.is_default"
		},
		"442": {
			"sourceFileName": "../../../../packages/modules/store/src/models/locale.ts",
			"qualifiedName": "__object.store"
		},
		"443": {
			"sourceFileName": "../../../../packages/modules/store/src/models/locale.ts",
			"qualifiedName": "__function"
		},
		"444": {
			"sourceFileName": "../../../../packages/modules/store/src/models/locale.ts",
			"qualifiedName": "__function"
		},
		"445": {
			"sourceFileName": "../../../../packages/modules/store/src/models/store.ts",
			"qualifiedName": "__object"
		},
		"446": {
			"sourceFileName": "../../../../packages/modules/store/src/models/store.ts",
			"qualifiedName": "__object.id"
		},
		"447": {
			"sourceFileName": "../../../../packages/modules/store/src/models/store.ts",
			"qualifiedName": "__object.name"
		},
		"448": {
			"sourceFileName": "../../../../packages/modules/store/src/models/store.ts",
			"qualifiedName": "__object.default_sales_channel_id"
		},
		"449": {
			"sourceFileName": "../../../../packages/modules/store/src/models/store.ts",
			"qualifiedName": "__object.default_region_id"
		},
		"450": {
			"sourceFileName": "../../../../packages/modules/store/src/models/store.ts",
			"qualifiedName": "__object.default_location_id"
		},
		"451": {
			"sourceFileName": "../../../../packages/modules/store/src/models/store.ts",
			"qualifiedName": "__object.metadata"
		},
		"452": {
			"sourceFileName": "../../../../packages/modules/store/src/models/store.ts",
			"qualifiedName": "__object.supported_currencies"
		},
		"453": {
			"sourceFileName": "../../../../packages/modules/store/src/models/store.ts",
			"qualifiedName": "__function"
		},
		"454": {
			"sourceFileName": "../../../../packages/modules/store/src/models/store.ts",
			"qualifiedName": "__function"
		},
		"455": {
			"sourceFileName": "../../../../packages/modules/store/src/models/store.ts",
			"qualifiedName": "__object.supported_locales"
		},
		"456": {
			"sourceFileName": "../../../../packages/modules/store/src/models/store.ts",
			"qualifiedName": "__function"
		},
		"457": {
			"sourceFileName": "../../../../packages/modules/store/src/models/store.ts",
			"qualifiedName": "__function"
		},
		"458": {
			"sourceFileName": "../../../../packages/modules/store/src/models/locale.ts",
			"qualifiedName": "__function"
		},
		"459": {
			"sourceFileName": "../../../../packages/modules/store/src/models/locale.ts",
			"qualifiedName": "__function"
		},
		"460": {
			"sourceFileName": "../../../../packages/modules/store/src/models/store.ts",
			"qualifiedName": "__object"
		},
		"461": {
			"sourceFileName": "../../../../packages/modules/store/src/models/store.ts",
			"qualifiedName": "__object.id"
		},
		"462": {
			"sourceFileName": "../../../../packages/modules/store/src/models/store.ts",
			"qualifiedName": "__object.name"
		},
		"463": {
			"sourceFileName": "../../../../packages/modules/store/src/models/store.ts",
			"qualifiedName": "__object.default_sales_channel_id"
		},
		"464": {
			"sourceFileName": "../../../../packages/modules/store/src/models/store.ts",
			"qualifiedName": "__object.default_region_id"
		},
		"465": {
			"sourceFileName": "../../../../packages/modules/store/src/models/store.ts",
			"qualifiedName": "__object.default_location_id"
		},
		"466": {
			"sourceFileName": "../../../../packages/modules/store/src/models/store.ts",
			"qualifiedName": "__object.metadata"
		},
		"467": {
			"sourceFileName": "../../../../packages/modules/store/src/models/store.ts",
			"qualifiedName": "__object.supported_currencies"
		},
		"468": {
			"sourceFileName": "../../../../packages/modules/store/src/models/store.ts",
			"qualifiedName": "__function"
		},
		"469": {
			"sourceFileName": "../../../../packages/modules/store/src/models/store.ts",
			"qualifiedName": "__function"
		},
		"470": {
			"sourceFileName": "../../../../packages/modules/store/src/models/store.ts",
			"qualifiedName": "__object.supported_locales"
		},
		"471": {
			"sourceFileName": "../../../../packages/modules/store/src/models/store.ts",
			"qualifiedName": "__function"
		},
		"472": {
			"sourceFileName": "../../../../packages/modules/store/src/models/store.ts",
			"qualifiedName": "__function"
		}
	},
	"files": {
		"entries": {
			"1": "../../../../packages/modules/store/src/models/index.ts"
		},
		"reflections": {
			"1": 368
		}
	}
}
